keras28models/__init__.py
keras28models/models28.py
Keras28Models-0.1.0.dist-info/LICENSE.txt
Keras28Models-0.1.0.dist-info/METADATA
Keras28Models-0.1.0.dist-info/WHEEL
Keras28Models-0.1.0.dist-info/top_level.txt
Keras28Models-0.1.0.dist-info/RECORD
