Metadata-Version: 2.1
Name: Keras28Models
Version: 0.1.0
Summary: All Traditional Classification Models 
Home-page: https://github.com/falahgs/
Author: Falahgs.G.Saleih
Author-email: falahgs07@gmail.com
License: MIT
Keywords: Keras,Tensorflow,Classification
Platform: UNKNOWN
Classifier: Programming Language :: Python :: 3
Classifier: License :: OSI Approved :: MIT License
Classifier: Operating System :: OS Independent
Requires-Python: >=3.6
Requires-Dist: keras
Requires-Dist: tensorflow (==2.2.0)
Requires-Dist: pandas
Requires-Dist: numpy
